ctgan/__init__.py
ctgan/__main__.py
ctgan/data.py
ctgan/data_sampler.py
ctgan/data_transformer.py
ctgan/demo.py
ctgan/synthesizers/__init__.py
ctgan/synthesizers/base.py
ctgan/synthesizers/ctgan.py
ctgan/synthesizers/tvae.py
ctgan-0.10.2.dist-info/LICENSE
ctgan-0.10.2.dist-info/METADATA
ctgan-0.10.2.dist-info/WHEEL
ctgan-0.10.2.dist-info/entry_points.txt
ctgan-0.10.2.dist-info/top_level.txt
ctgan-0.10.2.dist-info/RECORD
